clicksendapi/__init__.py
clicksendapi/api_helper.py
clicksendapi/clicksendapi_client.py
clicksendapi/configuration.py
clicksendapi/decorators.py
clicksendapi/controllers/__init__.py
clicksendapi/controllers/account_controller.py
clicksendapi/controllers/base_controller.py
clicksendapi/controllers/contact_controller.py
clicksendapi/exceptions/__init__.py
clicksendapi/exceptions/api_exception.py
clicksendapi/http/__init__.py
clicksendapi/http/http_call_back.py
clicksendapi/http/http_client.py
clicksendapi/http/http_method_enum.py
clicksendapi/http/http_request.py
clicksendapi/http/http_response.py
clicksendapi/http/requests_client.py
clicksendapi/http/auth/__init__.py
clicksendapi/http/auth/basic_auth.py
clicksendapi/models/__init__.py
clicksendapi/models/account_info.py
clicksendapi/models/account_verification_info.py
clicksendapi/models/new_contact_info.py
clicksendapi/utilities/__init__.py
clicksendapi/utilities/file_wrapper.py
apimaticclickSendAPI-1.0.0.dist-info/LICENSE
apimaticclickSendAPI-1.0.0.dist-info/METADATA
apimaticclickSendAPI-1.0.0.dist-info/WHEEL
apimaticclickSendAPI-1.0.0.dist-info/top_level.txt
apimaticclickSendAPI-1.0.0.dist-info/RECORD
